streamlit-x-flow/__init__.py
streamlit-x-flow/frontend/build/asset-manifest.json
streamlit-x-flow/frontend/build/favicon.ico
streamlit-x-flow/frontend/build/index.html
streamlit-x-flow/frontend/build/static/css/main.45306be9.css
streamlit-x-flow/frontend/build/static/css/main.45306be9.css.map
streamlit-x-flow/frontend/build/static/js/main.23e3e984.js
streamlit-x-flow/frontend/build/static/js/main.23e3e984.js.LICENSE.txt
streamlit-x-flow/frontend/build/static/js/main.23e3e984.js.map
streamlit_x_flow/__init__.py
streamlit_x_flow/frontend/build/asset-manifest.json
streamlit_x_flow/frontend/build/favicon.ico
streamlit_x_flow/frontend/build/index.html
streamlit_x_flow/frontend/build/static/css/main.45306be9.css
streamlit_x_flow/frontend/build/static/css/main.45306be9.css.map
streamlit_x_flow/frontend/build/static/js/main.23e3e984.js
streamlit_x_flow/frontend/build/static/js/main.23e3e984.js.LICENSE.txt
streamlit_x_flow/frontend/build/static/js/main.23e3e984.js.map
stxflow-0.0.2.dist-info/LICENSE
stxflow-0.0.2.dist-info/METADATA
stxflow-0.0.2.dist-info/WHEEL
stxflow-0.0.2.dist-info/top_level.txt
stxflow-0.0.2.dist-info/RECORD
