Metadata-Version: 2.1
Name: stxflow
Version: 0.0.2
Summary: Streamlit component xflow
Home-page: UNKNOWN
Author: zhoupengfei1991
Author-email: 2451718741@qq.com
License: UNKNOWN
Platform: UNKNOWN
Requires-Python: >=3.6
Requires-Dist: streamlit (>=0.63)
